Metadata-Version: 1.1
Name: mycelery
Version: 1.0.5
Summary: For mycelery! For Tim
Home-page: https://github.com/leiwenzheng/mycelery.git
Author: Lei wenzheng
Author-email: leiwz@kaisagroup.com
License: Apache License, Version 2.0
Platform: UNKNOWN
Classifier: Development Status :: 3 - Alpha
Classifier: Environment :: Web Environment
Classifier: Intended Audience :: Developers
Classifier: Operating System :: OS Independent
Classifier: Programming Language :: Python
